{"nodes":[{"id":34,"node_type":"Input"},{"id":39,"node_type":"Input"},{"id":64,"node_type":"Output"},{"id":65,"node_type":"Hidden"},{"id":14,"node_type":"Input"},{"id":13,"node_type":"Input"},{"id":24,"node_type":"Input"},{"id":58,"node_type":"Input"},{"id":66,"node_type":"Hidden"},{"id":52,"node_type":"Input"},{"id":12,"node_type":"Input"},{"id":43,"node_type":"Input"},{"id":2,"node_type":"Input"},{"id":22,"node_type":"Input"},{"id":0,"node_type":"Input"},{"id":49,"node_type":"Input"},{"id":28,"node_type":"Input"},{"id":16,"node_type":"Input"},{"id":56,"node_type":"Input"},{"id":37,"node_type":"Input"},{"id":38,"node_type":"Input"},{"id":27,"node_type":"Input"},{"id":54,"node_type":"Input"},{"id":3,"node_type":"Input"},{"id":26,"node_type":"Input"},{"id":32,"node_type":"Input"},{"id":60,"node_type":"Input"},{"id":46,"node_type":"Input"},{"id":33,"node_type":"Input"},{"id":57,"node_type":"Input"},{"id":7,"node_type":"Input"},{"id":18,"node_type":"Input"},{"id":11,"node_type":"Input"},{"id":47,"node_type":"Input"},{"id":31,"node_type":"Input"},{"id":17,"node_type":"Input"},{"id":30,"node_type":"Input"},{"id":55,"node_type":"Input"},{"id":8,"node_type":"Input"},{"id":42,"node_type":"Input"},{"id":50,"node_type":"Input"},{"id":36,"node_type":"Input"},{"id":53,"node_type":"Input"},{"id":62,"node_type":"Output"},{"id":4,"node_type":"Input"},{"id":1,"node_type":"Input"},{"id":25,"node_type":"Input"},{"id":59,"node_type":"Input"},{"id":15,"node_type":"Input"},{"id":41,"node_type":"Input"},{"id":23,"node_type":"Input"},{"id":51,"node_type":"Input"},{"id":29,"node_type":"Input"},{"id":6,"node_type":"Input"},{"id":20,"node_type":"Input"},{"id":45,"node_type":"Input"},{"id":61,"node_type":"Input"},{"id":44,"node_type":"Input"},{"id":10,"node_type":"Input"},{"id":9,"node_type":"Input"},{"id":21,"node_type":"Input"},{"id":63,"node_type":"Output"},{"id":35,"node_type":"Input"},{"id":48,"node_type":"Input"},{"id":5,"node_type":"Input"},{"id":40,"node_type":"Input"},{"id":19,"node_type":"Input"}],"conns":[{"in_node":0,"out_node":62,"weight":0.5387955,"enabled":true,"innovation":0},{"in_node":0,"out_node":63,"weight":-0.023683548,"enabled":true,"innovation":1},{"in_node":0,"out_node":64,"weight":0.99499416,"enabled":true,"innovation":2},{"in_node":1,"out_node":62,"weight":0.41146326,"enabled":true,"innovation":3},{"in_node":1,"out_node":63,"weight":-0.18304324,"enabled":true,"innovation":4},{"in_node":1,"out_node":64,"weight":0.47109675,"enabled":true,"innovation":5},{"in_node":2,"out_node":62,"weight":-0.07757497,"enabled":true,"innovation":6},{"in_node":2,"out_node":63,"weight":-0.621799,"enabled":true,"innovation":7},{"in_node":2,"out_node":64,"weight":-0.46749854,"enabled":true,"innovation":8},{"in_node":3,"out_node":62,"weight":0.5572603,"enabled":true,"innovation":9},{"in_node":3,"out_node":63,"weight":-0.033765078,"enabled":true,"innovation":10},{"in_node":3,"out_node":64,"weight":0.5474777,"enabled":true,"innovation":11},{"in_node":4,"out_node":62,"weight":-0.43295574,"enabled":true,"innovation":12},{"in_node":4,"out_node":63,"weight":0.96869516,"enabled":true,"innovation":13},{"in_node":4,"out_node":64,"weight":0.5574131,"enabled":true,"innovation":14},{"in_node":5,"out_node":62,"weight":0.97996235,"enabled":true,"innovation":15},{"in_node":5,"out_node":63,"weight":-0.5410719,"enabled":true,"innovation":16},{"in_node":5,"out_node":64,"weight":0.03437519,"enabled":true,"innovation":17},{"in_node":6,"out_node":62,"weight":0.11499548,"enabled":true,"innovation":18},{"in_node":6,"out_node":63,"weight":0.76118326,"enabled":true,"innovation":19},{"in_node":6,"out_node":64,"weight":-0.69738007,"enabled":true,"innovation":20},{"in_node":7,"out_node":62,"weight":-0.4369893,"enabled":true,"innovation":21},{"in_node":7,"out_node":63,"weight":0.35835266,"enabled":true,"innovation":22},{"in_node":7,"out_node":64,"weight":-0.95636773,"enabled":true,"innovation":23},{"in_node":8,"out_node":62,"weight":-0.20337129,"enabled":true,"innovation":24},{"in_node":8,"out_node":63,"weight":0.9081969,"enabled":true,"innovation":25},{"in_node":8,"out_node":64,"weight":0.19923568,"enabled":true,"innovation":26},{"in_node":9,"out_node":62,"weight":-0.82074,"enabled":true,"innovation":27},{"in_node":9,"out_node":63,"weight":0.3529048,"enabled":true,"innovation":28},{"in_node":9,"out_node":64,"weight":-0.038355112,"enabled":true,"innovation":29},{"in_node":10,"out_node":62,"weight":-0.5152426,"enabled":true,"innovation":30},{"in_node":10,"out_node":63,"weight":0.7829013,"enabled":true,"innovation":31},{"in_node":10,"out_node":64,"weight":0.7377641,"enabled":true,"innovation":32},{"in_node":11,"out_node":62,"weight":0.20028472,"enabled":true,"innovation":33},{"in_node":11,"out_node":63,"weight":0.025425911,"enabled":true,"innovation":34},{"in_node":11,"out_node":64,"weight":-0.44192863,"enabled":true,"innovation":35},{"in_node":12,"out_node":62,"weight":0.6315601,"enabled":true,"innovation":36},{"in_node":12,"out_node":63,"weight":0.8958945,"enabled":true,"innovation":37},{"in_node":12,"out_node":64,"weight":-0.4858148,"enabled":true,"innovation":38},{"in_node":13,"out_node":62,"weight":0.6722989,"enabled":true,"innovation":39},{"in_node":13,"out_node":63,"weight":0.52033687,"enabled":true,"innovation":40},{"in_node":13,"out_node":64,"weight":-0.5597391,"enabled":true,"innovation":41},{"in_node":14,"out_node":62,"weight":0.32573438,"enabled":true,"innovation":42},{"in_node":14,"out_node":63,"weight":0.48711753,"enabled":true,"innovation":43},{"in_node":14,"out_node":64,"weight":0.27376366,"enabled":true,"innovation":44},{"in_node":15,"out_node":62,"weight":0.24944353,"enabled":true,"innovation":45},{"in_node":15,"out_node":63,"weight":0.7732611,"enabled":true,"innovation":46},{"in_node":15,"out_node":64,"weight":0.7135346,"enabled":true,"innovation":47},{"in_node":16,"out_node":62,"weight":0.35157228,"enabled":true,"innovation":48},{"in_node":16,"out_node":63,"weight":-0.556021,"enabled":true,"innovation":49},{"in_node":16,"out_node":64,"weight":0.88788986,"enabled":true,"innovation":50},{"in_node":17,"out_node":62,"weight":0.87082624,"enabled":true,"innovation":51},{"in_node":17,"out_node":63,"weight":0.19054437,"enabled":true,"innovation":52},{"in_node":17,"out_node":64,"weight":0.4589877,"enabled":true,"innovation":53},{"in_node":18,"out_node":62,"weight":0.35127997,"enabled":true,"innovation":54},{"in_node":18,"out_node":63,"weight":-0.60113573,"enabled":true,"innovation":55},{"in_node":18,"out_node":64,"weight":-0.05856514,"enabled":true,"innovation":56},{"in_node":19,"out_node":62,"weight":-0.972533,"enabled":true,"innovation":57},{"in_node":19,"out_node":63,"weight":0.8164451,"enabled":true,"innovation":58},{"in_node":19,"out_node":64,"weight":-0.11018634,"enabled":true,"innovation":59},{"in_node":20,"out_node":62,"weight":-0.5802417,"enabled":true,"innovation":60},{"in_node":20,"out_node":63,"weight":0.28330922,"enabled":true,"innovation":61},{"in_node":20,"out_node":64,"weight":0.9933579,"enabled":true,"innovation":62},{"in_node":21,"out_node":62,"weight":0.76739573,"enabled":true,"innovation":63},{"in_node":21,"out_node":63,"weight":0.009218216,"enabled":true,"innovation":64},{"in_node":21,"out_node":64,"weight":-0.37221527,"enabled":true,"innovation":65},{"in_node":22,"out_node":62,"weight":0.23829365,"enabled":true,"innovation":66},{"in_node":22,"out_node":63,"weight":-0.5301292,"enabled":true,"innovation":67},{"in_node":22,"out_node":64,"weight":0.10645437,"enabled":false,"innovation":68},{"in_node":23,"out_node":62,"weight":-0.19115376,"enabled":true,"innovation":69},{"in_node":23,"out_node":63,"weight":0.85699534,"enabled":true,"innovation":70},{"in_node":23,"out_node":64,"weight":-0.6969545,"enabled":true,"innovation":71},{"in_node":24,"out_node":62,"weight":0.38876414,"enabled":true,"innovation":72},{"in_node":24,"out_node":63,"weight":-0.7703376,"enabled":true,"innovation":73},{"in_node":24,"out_node":64,"weight":0.086076975,"enabled":true,"innovation":74},{"in_node":25,"out_node":62,"weight":-0.76212,"enabled":true,"innovation":75},{"in_node":25,"out_node":63,"weight":0.5736537,"enabled":true,"innovation":76},{"in_node":25,"out_node":64,"weight":0.53973436,"enabled":true,"innovation":77},{"in_node":26,"out_node":62,"weight":-0.84968257,"enabled":true,"innovation":78},{"in_node":26,"out_node":63,"weight":0.24001527,"enabled":true,"innovation":79},{"in_node":26,"out_node":64,"weight":-0.2317636,"enabled":true,"innovation":80},{"in_node":27,"out_node":62,"weight":0.9658649,"enabled":true,"innovation":81},{"in_node":27,"out_node":63,"weight":0.3588779,"enabled":true,"innovation":82},{"in_node":27,"out_node":64,"weight":0.04375148,"enabled":true,"innovation":83},{"in_node":28,"out_node":62,"weight":0.7278528,"enabled":true,"innovation":84},{"in_node":28,"out_node":63,"weight":0.50943065,"enabled":true,"innovation":85},{"in_node":28,"out_node":64,"weight":-0.5595944,"enabled":true,"innovation":86},{"in_node":29,"out_node":62,"weight":-0.23471928,"enabled":true,"innovation":87},{"in_node":29,"out_node":63,"weight":0.97630906,"enabled":true,"innovation":88},{"in_node":29,"out_node":64,"weight":-0.7862332,"enabled":true,"innovation":89},{"in_node":30,"out_node":62,"weight":-0.8110852,"enabled":true,"innovation":90},{"in_node":30,"out_node":63,"weight":0.90631604,"enabled":true,"innovation":91},{"in_node":30,"out_node":64,"weight":-0.26120758,"enabled":true,"innovation":92},{"in_node":31,"out_node":62,"weight":-0.043715954,"enabled":true,"innovation":93},{"in_node":31,"out_node":63,"weight":0.91887474,"enabled":true,"innovation":94},{"in_node":31,"out_node":64,"weight":-0.36284423,"enabled":true,"innovation":95},{"in_node":32,"out_node":62,"weight":-0.3797803,"enabled":true,"innovation":96},{"in_node":32,"out_node":63,"weight":-0.791023,"enabled":true,"innovation":97},{"in_node":32,"out_node":64,"weight":0.25725245,"enabled":false,"innovation":98},{"in_node":33,"out_node":62,"weight":-0.178653,"enabled":true,"innovation":99},{"in_node":33,"out_node":63,"weight":-0.74564934,"enabled":true,"innovation":100},{"in_node":33,"out_node":64,"weight":-0.2583034,"enabled":true,"innovation":101},{"in_node":34,"out_node":62,"weight":0.9030256,"enabled":true,"innovation":102},{"in_node":34,"out_node":63,"weight":-0.05735159,"enabled":true,"innovation":103},{"in_node":34,"out_node":64,"weight":0.77018905,"enabled":true,"innovation":104},{"in_node":35,"out_node":62,"weight":-0.37027717,"enabled":true,"innovation":105},{"in_node":35,"out_node":63,"weight":0.6707833,"enabled":true,"innovation":106},{"in_node":35,"out_node":64,"weight":0.299932,"enabled":true,"innovation":107},{"in_node":36,"out_node":62,"weight":0.43546534,"enabled":true,"innovation":108},{"in_node":36,"out_node":63,"weight":-0.5191686,"enabled":true,"innovation":109},{"in_node":36,"out_node":64,"weight":0.5875027,"enabled":true,"innovation":110},{"in_node":37,"out_node":62,"weight":0.5151315,"enabled":true,"innovation":111},{"in_node":37,"out_node":63,"weight":-0.31922126,"enabled":true,"innovation":112},{"in_node":37,"out_node":64,"weight":-0.5525758,"enabled":true,"innovation":113},{"in_node":38,"out_node":62,"weight":0.47930336,"enabled":true,"innovation":114},{"in_node":38,"out_node":63,"weight":-0.92359066,"enabled":true,"innovation":115},{"in_node":38,"out_node":64,"weight":-0.29550195,"enabled":true,"innovation":116},{"in_node":39,"out_node":62,"weight":-0.81653714,"enabled":true,"innovation":117},{"in_node":39,"out_node":63,"weight":-0.2716446,"enabled":true,"innovation":118},{"in_node":39,"out_node":64,"weight":-0.24212456,"enabled":true,"innovation":119},{"in_node":40,"out_node":62,"weight":0.17478609,"enabled":true,"innovation":120},{"in_node":40,"out_node":63,"weight":0.2114954,"enabled":true,"innovation":121},{"in_node":40,"out_node":64,"weight":-0.5119729,"enabled":true,"innovation":122},{"in_node":41,"out_node":62,"weight":-0.11634922,"enabled":true,"innovation":123},{"in_node":41,"out_node":63,"weight":-0.25630212,"enabled":true,"innovation":124},{"in_node":41,"out_node":64,"weight":0.8904269,"enabled":true,"innovation":125},{"in_node":42,"out_node":62,"weight":0.039972067,"enabled":true,"innovation":126},{"in_node":42,"out_node":63,"weight":0.77877975,"enabled":true,"innovation":127},{"in_node":42,"out_node":64,"weight":-0.8202195,"enabled":true,"innovation":128},{"in_node":43,"out_node":62,"weight":-0.5688472,"enabled":true,"innovation":129},{"in_node":43,"out_node":63,"weight":0.356431,"enabled":true,"innovation":130},{"in_node":43,"out_node":64,"weight":0.93189096,"enabled":true,"innovation":131},{"in_node":44,"out_node":62,"weight":0.82413363,"enabled":true,"innovation":132},{"in_node":44,"out_node":63,"weight":-0.12786627,"enabled":true,"innovation":133},{"in_node":44,"out_node":64,"weight":0.45355105,"enabled":true,"innovation":134},{"in_node":45,"out_node":62,"weight":0.5750253,"enabled":true,"innovation":135},{"in_node":45,"out_node":63,"weight":-0.4287448,"enabled":true,"innovation":136},{"in_node":45,"out_node":64,"weight":-0.07056713,"enabled":true,"innovation":137},{"in_node":46,"out_node":62,"weight":0.80728984,"enabled":true,"innovation":138},{"in_node":46,"out_node":63,"weight":0.9331882,"enabled":true,"innovation":139},{"in_node":46,"out_node":64,"weight":0.6376488,"enabled":true,"innovation":140},{"in_node":47,"out_node":62,"weight":0.13055539,"enabled":true,"innovation":141},{"in_node":47,"out_node":63,"weight":-0.5369916,"enabled":true,"innovation":142},{"in_node":47,"out_node":64,"weight":-0.7908511,"enabled":true,"innovation":143},{"in_node":48,"out_node":62,"weight":-0.6646354,"enabled":true,"innovation":144},{"in_node":48,"out_node":63,"weight":0.77517676,"enabled":true,"innovation":145},{"in_node":48,"out_node":64,"weight":0.096704245,"enabled":true,"innovation":146},{"in_node":49,"out_node":62,"weight":-0.18786931,"enabled":true,"innovation":147},{"in_node":49,"out_node":63,"weight":-0.55989623,"enabled":true,"innovation":148},{"in_node":49,"out_node":64,"weight":0.757015,"enabled":true,"innovation":149},{"in_node":50,"out_node":62,"weight":-0.6647825,"enabled":true,"innovation":150},{"in_node":50,"out_node":63,"weight":0.6773317,"enabled":true,"innovation":151},{"in_node":50,"out_node":64,"weight":0.44379306,"enabled":true,"innovation":152},{"in_node":51,"out_node":62,"weight":-0.35581136,"enabled":true,"innovation":153},{"in_node":51,"out_node":63,"weight":0.9434719,"enabled":true,"innovation":154},{"in_node":51,"out_node":64,"weight":-0.35009956,"enabled":true,"innovation":155},{"in_node":52,"out_node":62,"weight":-0.29750133,"enabled":true,"innovation":156},{"in_node":52,"out_node":63,"weight":-0.5161216,"enabled":true,"innovation":157},{"in_node":52,"out_node":64,"weight":-0.36172247,"enabled":true,"innovation":158},{"in_node":53,"out_node":62,"weight":0.8355613,"enabled":true,"innovation":159},{"in_node":53,"out_node":63,"weight":-0.051448107,"enabled":true,"innovation":160},{"in_node":53,"out_node":64,"weight":-0.3658023,"enabled":true,"innovation":161},{"in_node":54,"out_node":62,"weight":-0.22586656,"enabled":true,"innovation":162},{"in_node":54,"out_node":63,"weight":-0.086420774,"enabled":true,"innovation":163},{"in_node":54,"out_node":64,"weight":-0.6189997,"enabled":true,"innovation":164},{"in_node":55,"out_node":62,"weight":0.35481763,"enabled":true,"innovation":165},{"in_node":55,"out_node":63,"weight":-0.09650469,"enabled":true,"innovation":166},{"in_node":55,"out_node":64,"weight":0.7498174,"enabled":true,"innovation":167},{"in_node":56,"out_node":62,"weight":0.80271864,"enabled":true,"innovation":168},{"in_node":56,"out_node":63,"weight":0.8593142,"enabled":true,"innovation":169},{"in_node":56,"out_node":64,"weight":0.71644616,"enabled":true,"innovation":170},{"in_node":57,"out_node":62,"weight":0.039456367,"enabled":true,"innovation":171},{"in_node":57,"out_node":63,"weight":0.5530107,"enabled":true,"innovation":172},{"in_node":57,"out_node":64,"weight":-0.7794976,"enabled":true,"innovation":173},{"in_node":58,"out_node":62,"weight":0.34660864,"enabled":true,"innovation":174},{"in_node":58,"out_node":63,"weight":-0.83896875,"enabled":true,"innovation":175},{"in_node":58,"out_node":64,"weight":-0.41887832,"enabled":true,"innovation":176},{"in_node":59,"out_node":62,"weight":-0.5741234,"enabled":true,"innovation":177},{"in_node":59,"out_node":63,"weight":0.050457,"enabled":true,"innovation":178},{"in_node":59,"out_node":64,"weight":-0.23872209,"enabled":true,"innovation":179},{"in_node":60,"out_node":62,"weight":-0.40432048,"enabled":true,"innovation":180},{"in_node":60,"out_node":63,"weight":0.44679666,"enabled":true,"innovation":181},{"in_node":60,"out_node":64,"weight":-0.909467,"enabled":true,"innovation":182},{"in_node":61,"out_node":62,"weight":-0.94726276,"enabled":true,"innovation":183},{"in_node":61,"out_node":63,"weight":-0.31459856,"enabled":true,"innovation":184},{"in_node":61,"out_node":64,"weight":0.015401125,"enabled":true,"innovation":185},{"in_node":22,"out_node":65,"weight":1.0,"enabled":true,"innovation":186},{"in_node":65,"out_node":64,"weight":0.10645437,"enabled":true,"innovation":187},{"in_node":59,"out_node":65,"weight":-0.8598335,"enabled":true,"innovation":188},{"in_node":32,"out_node":66,"weight":1.0,"enabled":true,"innovation":189},{"in_node":66,"out_node":64,"weight":0.25725245,"enabled":true,"innovation":190},{"in_node":25,"out_node":66,"weight":-0.73984385,"enabled":true,"innovation":191}],"fitness":50.75556,"fitness_naive":50.09991}