{"nodes":[{"id":52,"node_type":"Input"},{"id":85,"node_type":"Hidden"},{"id":16,"node_type":"Input"},{"id":19,"node_type":"Input"},{"id":54,"node_type":"Input"},{"id":41,"node_type":"Input"},{"id":23,"node_type":"Input"},{"id":44,"node_type":"Input"},{"id":46,"node_type":"Input"},{"id":48,"node_type":"Input"},{"id":0,"node_type":"Input"},{"id":3,"node_type":"Input"},{"id":75,"node_type":"Hidden"},{"id":68,"node_type":"Hidden"},{"id":20,"node_type":"Input"},{"id":36,"node_type":"Input"},{"id":30,"node_type":"Input"},{"id":49,"node_type":"Input"},{"id":60,"node_type":"Input"},{"id":58,"node_type":"Input"},{"id":79,"node_type":"Hidden"},{"id":39,"node_type":"Input"},{"id":32,"node_type":"Input"},{"id":65,"node_type":"Hidden"},{"id":5,"node_type":"Input"},{"id":9,"node_type":"Input"},{"id":55,"node_type":"Input"},{"id":43,"node_type":"Input"},{"id":66,"node_type":"Hidden"},{"id":45,"node_type":"Input"},{"id":29,"node_type":"Input"},{"id":27,"node_type":"Input"},{"id":33,"node_type":"Input"},{"id":63,"node_type":"Output"},{"id":10,"node_type":"Input"},{"id":69,"node_type":"Hidden"},{"id":87,"node_type":"Hidden"},{"id":76,"node_type":"Hidden"},{"id":22,"node_type":"Input"},{"id":84,"node_type":"Hidden"},{"id":83,"node_type":"Hidden"},{"id":56,"node_type":"Input"},{"id":70,"node_type":"Hidden"},{"id":1,"node_type":"Input"},{"id":86,"node_type":"Hidden"},{"id":82,"node_type":"Hidden"},{"id":61,"node_type":"Input"},{"id":25,"node_type":"Input"},{"id":42,"node_type":"Input"},{"id":37,"node_type":"Input"},{"id":67,"node_type":"Hidden"},{"id":4,"node_type":"Input"},{"id":88,"node_type":"Hidden"},{"id":15,"node_type":"Input"},{"id":51,"node_type":"Input"},{"id":2,"node_type":"Input"},{"id":64,"node_type":"Output"},{"id":7,"node_type":"Input"},{"id":77,"node_type":"Hidden"},{"id":50,"node_type":"Input"},{"id":71,"node_type":"Hidden"},{"id":38,"node_type":"Input"},{"id":8,"node_type":"Input"},{"id":47,"node_type":"Input"},{"id":53,"node_type":"Input"},{"id":81,"node_type":"Hidden"},{"id":78,"node_type":"Hidden"},{"id":17,"node_type":"Input"},{"id":26,"node_type":"Input"},{"id":57,"node_type":"Input"},{"id":62,"node_type":"Output"},{"id":13,"node_type":"Input"},{"id":28,"node_type":"Input"},{"id":24,"node_type":"Input"},{"id":89,"node_type":"Hidden"},{"id":34,"node_type":"Input"},{"id":14,"node_type":"Input"},{"id":74,"node_type":"Hidden"},{"id":40,"node_type":"Input"},{"id":35,"node_type":"Input"},{"id":21,"node_type":"Input"},{"id":6,"node_type":"Input"},{"id":11,"node_type":"Input"},{"id":72,"node_type":"Hidden"},{"id":59,"node_type":"Input"},{"id":18,"node_type":"Input"},{"id":12,"node_type":"Input"},{"id":80,"node_type":"Hidden"},{"id":73,"node_type":"Hidden"},{"id":31,"node_type":"Input"}],"conns":[{"in_node":0,"out_node":62,"weight":-0.78903294,"enabled":true,"innovation":0},{"in_node":0,"out_node":63,"weight":0.5586655,"enabled":true,"innovation":1},{"in_node":0,"out_node":64,"weight":0.77101874,"enabled":true,"innovation":2},{"in_node":1,"out_node":62,"weight":0.1997416,"enabled":true,"innovation":3},{"in_node":1,"out_node":63,"weight":-0.9651251,"enabled":true,"innovation":4},{"in_node":1,"out_node":64,"weight":0.93120074,"enabled":true,"innovation":5},{"in_node":2,"out_node":62,"weight":-0.14625669,"enabled":true,"innovation":6},{"in_node":2,"out_node":63,"weight":-0.2500317,"enabled":true,"innovation":7},{"in_node":2,"out_node":64,"weight":-0.62224793,"enabled":true,"innovation":8},{"in_node":3,"out_node":62,"weight":0.09027934,"enabled":true,"innovation":9},{"in_node":3,"out_node":63,"weight":0.4778297,"enabled":true,"innovation":10},{"in_node":3,"out_node":64,"weight":0.7873237,"enabled":true,"innovation":11},{"in_node":4,"out_node":62,"weight":0.681782,"enabled":true,"innovation":12},{"in_node":4,"out_node":63,"weight":-0.75091004,"enabled":true,"innovation":13},{"in_node":4,"out_node":64,"weight":0.2854991,"enabled":true,"innovation":14},{"in_node":5,"out_node":62,"weight":-0.040920258,"enabled":true,"innovation":15},{"in_node":5,"out_node":63,"weight":0.7982583,"enabled":true,"innovation":16},{"in_node":5,"out_node":64,"weight":0.73338413,"enabled":true,"innovation":17},{"in_node":6,"out_node":62,"weight":0.21970272,"enabled":true,"innovation":18},{"in_node":6,"out_node":63,"weight":-0.23541522,"enabled":true,"innovation":19},{"in_node":6,"out_node":64,"weight":-0.74038553,"enabled":true,"innovation":20},{"in_node":7,"out_node":62,"weight":-0.23226333,"enabled":true,"innovation":21},{"in_node":7,"out_node":63,"weight":0.38794756,"enabled":true,"innovation":22},{"in_node":7,"out_node":64,"weight":0.55442834,"enabled":true,"innovation":23},{"in_node":8,"out_node":62,"weight":0.15646648,"enabled":true,"innovation":24},{"in_node":8,"out_node":63,"weight":-0.6889558,"enabled":true,"innovation":25},{"in_node":8,"out_node":64,"weight":-0.064413786,"enabled":true,"innovation":26},{"in_node":9,"out_node":62,"weight":-0.3427608,"enabled":true,"innovation":27},{"in_node":9,"out_node":63,"weight":0.3153696,"enabled":true,"innovation":28},{"in_node":9,"out_node":64,"weight":0.28192067,"enabled":false,"innovation":29},{"in_node":10,"out_node":62,"weight":-0.16618586,"enabled":true,"innovation":30},{"in_node":10,"out_node":63,"weight":0.9629204,"enabled":true,"innovation":31},{"in_node":10,"out_node":64,"weight":0.3490677,"enabled":true,"innovation":32},{"in_node":11,"out_node":62,"weight":0.19510198,"enabled":true,"innovation":33},{"in_node":11,"out_node":63,"weight":0.15410137,"enabled":true,"innovation":34},{"in_node":11,"out_node":64,"weight":-0.5382402,"enabled":true,"innovation":35},{"in_node":12,"out_node":62,"weight":-0.1544137,"enabled":true,"innovation":36},{"in_node":12,"out_node":63,"weight":0.92820454,"enabled":true,"innovation":37},{"in_node":12,"out_node":64,"weight":-0.5202391,"enabled":false,"innovation":38},{"in_node":13,"out_node":62,"weight":0.11187005,"enabled":true,"innovation":39},{"in_node":13,"out_node":63,"weight":0.0111835,"enabled":true,"innovation":40},{"in_node":13,"out_node":64,"weight":0.61158943,"enabled":true,"innovation":41},{"in_node":14,"out_node":62,"weight":0.8703108,"enabled":true,"innovation":42},{"in_node":14,"out_node":63,"weight":-0.6384585,"enabled":true,"innovation":43},{"in_node":14,"out_node":64,"weight":0.40370154,"enabled":true,"innovation":44},{"in_node":15,"out_node":62,"weight":0.048717976,"enabled":true,"innovation":45},{"in_node":15,"out_node":63,"weight":0.1678009,"enabled":true,"innovation":46},{"in_node":15,"out_node":64,"weight":0.896101,"enabled":true,"innovation":47},{"in_node":16,"out_node":62,"weight":0.40454817,"enabled":true,"innovation":48},{"in_node":16,"out_node":63,"weight":-0.20816779,"enabled":true,"innovation":49},{"in_node":16,"out_node":64,"weight":-0.75380373,"enabled":true,"innovation":50},{"in_node":17,"out_node":62,"weight":0.15280962,"enabled":true,"innovation":51},{"in_node":17,"out_node":63,"weight":-0.9115784,"enabled":true,"innovation":52},{"in_node":17,"out_node":64,"weight":-0.2399962,"enabled":true,"innovation":53},{"in_node":18,"out_node":62,"weight":0.99555755,"enabled":true,"innovation":54},{"in_node":18,"out_node":63,"weight":-0.22911239,"enabled":true,"innovation":55},{"in_node":18,"out_node":64,"weight":0.063991785,"enabled":true,"innovation":56},{"in_node":19,"out_node":62,"weight":0.16197824,"enabled":true,"innovation":57},{"in_node":19,"out_node":63,"weight":0.8144152,"enabled":true,"innovation":58},{"in_node":19,"out_node":64,"weight":0.17651463,"enabled":true,"innovation":59},{"in_node":20,"out_node":62,"weight":0.020843506,"enabled":true,"innovation":60},{"in_node":20,"out_node":63,"weight":0.06359339,"enabled":true,"innovation":61},{"in_node":20,"out_node":64,"weight":0.22446656,"enabled":true,"innovation":62},{"in_node":21,"out_node":62,"weight":0.9633646,"enabled":true,"innovation":63},{"in_node":21,"out_node":63,"weight":0.49849033,"enabled":true,"innovation":64},{"in_node":21,"out_node":64,"weight":0.044503212,"enabled":true,"innovation":65},{"in_node":22,"out_node":62,"weight":-0.85097694,"enabled":true,"innovation":66},{"in_node":22,"out_node":63,"weight":0.9611883,"enabled":true,"innovation":67},{"in_node":22,"out_node":64,"weight":-0.7496166,"enabled":true,"innovation":68},{"in_node":23,"out_node":62,"weight":-0.55918455,"enabled":true,"innovation":69},{"in_node":23,"out_node":63,"weight":0.4814515,"enabled":true,"innovation":70},{"in_node":23,"out_node":64,"weight":0.03682089,"enabled":true,"innovation":71},{"in_node":24,"out_node":62,"weight":-0.6649082,"enabled":true,"innovation":72},{"in_node":24,"out_node":63,"weight":-0.42206812,"enabled":true,"innovation":73},{"in_node":24,"out_node":64,"weight":0.11838579,"enabled":true,"innovation":74},{"in_node":25,"out_node":62,"weight":0.5630231,"enabled":true,"innovation":75},{"in_node":25,"out_node":63,"weight":0.84015894,"enabled":true,"innovation":76},{"in_node":25,"out_node":64,"weight":0.70158553,"enabled":true,"innovation":77},{"in_node":26,"out_node":62,"weight":0.43297815,"enabled":true,"innovation":78},{"in_node":26,"out_node":63,"weight":0.26405835,"enabled":true,"innovation":79},{"in_node":26,"out_node":64,"weight":-0.10136318,"enabled":true,"innovation":80},{"in_node":27,"out_node":62,"weight":0.873116,"enabled":true,"innovation":81},{"in_node":27,"out_node":63,"weight":-0.18325663,"enabled":true,"innovation":82},{"in_node":27,"out_node":64,"weight":-0.70177364,"enabled":true,"innovation":83},{"in_node":28,"out_node":62,"weight":0.80901885,"enabled":true,"innovation":84},{"in_node":28,"out_node":63,"weight":0.94386554,"enabled":true,"innovation":85},{"in_node":28,"out_node":64,"weight":-0.48442817,"enabled":true,"innovation":86},{"in_node":29,"out_node":62,"weight":-0.9288213,"enabled":true,"innovation":87},{"in_node":29,"out_node":63,"weight":-0.24963784,"enabled":true,"innovation":88},{"in_node":29,"out_node":64,"weight":0.70993376,"enabled":true,"innovation":89},{"in_node":30,"out_node":62,"weight":0.9884701,"enabled":false,"innovation":90},{"in_node":30,"out_node":63,"weight":-0.17442918,"enabled":true,"innovation":91},{"in_node":30,"out_node":64,"weight":0.106972694,"enabled":true,"innovation":92},{"in_node":31,"out_node":62,"weight":-0.8525779,"enabled":true,"innovation":93},{"in_node":31,"out_node":63,"weight":-0.9622228,"enabled":true,"innovation":94},{"in_node":31,"out_node":64,"weight":-0.8703921,"enabled":true,"innovation":95},{"in_node":32,"out_node":62,"weight":-0.00471282,"enabled":true,"innovation":96},{"in_node":32,"out_node":63,"weight":-0.46194077,"enabled":true,"innovation":97},{"in_node":32,"out_node":64,"weight":-0.29551768,"enabled":true,"innovation":98},{"in_node":33,"out_node":62,"weight":0.30822635,"enabled":true,"innovation":99},{"in_node":33,"out_node":63,"weight":-0.2378931,"enabled":true,"innovation":100},{"in_node":33,"out_node":64,"weight":0.15280938,"enabled":true,"innovation":101},{"in_node":34,"out_node":62,"weight":-0.7902653,"enabled":true,"innovation":102},{"in_node":34,"out_node":63,"weight":-0.47428083,"enabled":true,"innovation":103},{"in_node":34,"out_node":64,"weight":0.47664523,"enabled":true,"innovation":104},{"in_node":35,"out_node":62,"weight":-0.22454166,"enabled":true,"innovation":105},{"in_node":35,"out_node":63,"weight":0.47471023,"enabled":false,"innovation":106},{"in_node":35,"out_node":64,"weight":0.24612474,"enabled":true,"innovation":107},{"in_node":36,"out_node":62,"weight":0.6669562,"enabled":false,"innovation":108},{"in_node":36,"out_node":63,"weight":0.15244508,"enabled":true,"innovation":109},{"in_node":36,"out_node":64,"weight":0.16236591,"enabled":true,"innovation":110},{"in_node":37,"out_node":62,"weight":-0.37753844,"enabled":true,"innovation":111},{"in_node":37,"out_node":63,"weight":0.7993014,"enabled":false,"innovation":112},{"in_node":37,"out_node":64,"weight":-0.8934915,"enabled":true,"innovation":113},{"in_node":38,"out_node":62,"weight":0.81922436,"enabled":true,"innovation":114},{"in_node":38,"out_node":63,"weight":-0.912447,"enabled":true,"innovation":115},{"in_node":38,"out_node":64,"weight":-0.61819315,"enabled":true,"innovation":116},{"in_node":39,"out_node":62,"weight":0.16794848,"enabled":true,"innovation":117},{"in_node":39,"out_node":63,"weight":0.68263316,"enabled":true,"innovation":118},{"in_node":39,"out_node":64,"weight":0.52408385,"enabled":true,"innovation":119},{"in_node":40,"out_node":62,"weight":0.2938094,"enabled":true,"innovation":120},{"in_node":40,"out_node":63,"weight":-0.20646954,"enabled":true,"innovation":121},{"in_node":40,"out_node":64,"weight":-0.30661654,"enabled":true,"innovation":122},{"in_node":41,"out_node":62,"weight":0.74047184,"enabled":true,"innovation":123},{"in_node":41,"out_node":63,"weight":-0.59950304,"enabled":true,"innovation":124},{"in_node":41,"out_node":64,"weight":0.83163595,"enabled":true,"innovation":125},{"in_node":42,"out_node":62,"weight":0.60972404,"enabled":true,"innovation":126},{"in_node":42,"out_node":63,"weight":0.5104339,"enabled":true,"innovation":127},{"in_node":42,"out_node":64,"weight":0.07588887,"enabled":true,"innovation":128},{"in_node":43,"out_node":62,"weight":-0.6196339,"enabled":true,"innovation":129},{"in_node":43,"out_node":63,"weight":-0.21951461,"enabled":true,"innovation":130},{"in_node":43,"out_node":64,"weight":-0.93523645,"enabled":true,"innovation":131},{"in_node":44,"out_node":62,"weight":-0.9206023,"enabled":true,"innovation":132},{"in_node":44,"out_node":63,"weight":0.2709601,"enabled":true,"innovation":133},{"in_node":44,"out_node":64,"weight":-0.9610057,"enabled":true,"innovation":134},{"in_node":45,"out_node":62,"weight":-0.15980053,"enabled":true,"innovation":135},{"in_node":45,"out_node":63,"weight":0.7516022,"enabled":true,"innovation":136},{"in_node":45,"out_node":64,"weight":0.73129296,"enabled":true,"innovation":137},{"in_node":46,"out_node":62,"weight":0.8124695,"enabled":true,"innovation":138},{"in_node":46,"out_node":63,"weight":0.5067179,"enabled":true,"innovation":139},{"in_node":46,"out_node":64,"weight":0.4720924,"enabled":true,"innovation":140},{"in_node":47,"out_node":62,"weight":-0.54857874,"enabled":true,"innovation":141},{"in_node":47,"out_node":63,"weight":0.01015234,"enabled":true,"innovation":142},{"in_node":47,"out_node":64,"weight":0.2027626,"enabled":true,"innovation":143},{"in_node":48,"out_node":62,"weight":0.61223817,"enabled":true,"innovation":144},{"in_node":48,"out_node":63,"weight":0.08728504,"enabled":true,"innovation":145},{"in_node":48,"out_node":64,"weight":-0.8284826,"enabled":true,"innovation":146},{"in_node":49,"out_node":62,"weight":-0.36962986,"enabled":true,"innovation":147},{"in_node":49,"out_node":63,"weight":-0.8427844,"enabled":true,"innovation":148},{"in_node":49,"out_node":64,"weight":-0.98475814,"enabled":true,"innovation":149},{"in_node":50,"out_node":62,"weight":-0.96392703,"enabled":true,"innovation":150},{"in_node":50,"out_node":63,"weight":0.34295607,"enabled":true,"innovation":151},{"in_node":50,"out_node":64,"weight":0.25356197,"enabled":true,"innovation":152},{"in_node":51,"out_node":62,"weight":0.7281599,"enabled":true,"innovation":153},{"in_node":51,"out_node":63,"weight":-0.08038688,"enabled":true,"innovation":154},{"in_node":51,"out_node":64,"weight":0.13643074,"enabled":true,"innovation":155},{"in_node":52,"out_node":62,"weight":0.27713394,"enabled":true,"innovation":156},{"in_node":52,"out_node":63,"weight":0.28392887,"enabled":true,"innovation":157},{"in_node":52,"out_node":64,"weight":-0.19319963,"enabled":true,"innovation":158},{"in_node":53,"out_node":62,"weight":0.3813622,"enabled":true,"innovation":159},{"in_node":53,"out_node":63,"weight":0.12841272,"enabled":true,"innovation":160},{"in_node":53,"out_node":64,"weight":-0.1815207,"enabled":true,"innovation":161},{"in_node":54,"out_node":62,"weight":-0.29579687,"enabled":true,"innovation":162},{"in_node":54,"out_node":63,"weight":-0.28996968,"enabled":true,"innovation":163},{"in_node":54,"out_node":64,"weight":-0.8643675,"enabled":true,"innovation":164},{"in_node":55,"out_node":62,"weight":0.13447046,"enabled":true,"innovation":165},{"in_node":55,"out_node":63,"weight":0.6571915,"enabled":true,"innovation":166},{"in_node":55,"out_node":64,"weight":-0.5353811,"enabled":true,"innovation":167},{"in_node":56,"out_node":62,"weight":0.33682418,"enabled":true,"innovation":168},{"in_node":56,"out_node":63,"weight":0.90707207,"enabled":true,"innovation":169},{"in_node":56,"out_node":64,"weight":-0.35948157,"enabled":true,"innovation":170},{"in_node":57,"out_node":62,"weight":-0.6546836,"enabled":true,"innovation":171},{"in_node":57,"out_node":63,"weight":0.7555926,"enabled":true,"innovation":172},{"in_node":57,"out_node":64,"weight":0.096897125,"enabled":true,"innovation":173},{"in_node":58,"out_node":62,"weight":0.7495899,"enabled":true,"innovation":174},{"in_node":58,"out_node":63,"weight":0.26395774,"enabled":true,"innovation":175},{"in_node":58,"out_node":64,"weight":0.998266,"enabled":true,"innovation":176},{"in_node":59,"out_node":62,"weight":-0.46391225,"enabled":true,"innovation":177},{"in_node":59,"out_node":63,"weight":-0.44320083,"enabled":true,"innovation":178},{"in_node":59,"out_node":64,"weight":0.9506388,"enabled":true,"innovation":179},{"in_node":60,"out_node":62,"weight":-0.838881,"enabled":false,"innovation":180},{"in_node":60,"out_node":63,"weight":-0.25174952,"enabled":true,"innovation":181},{"in_node":60,"out_node":64,"weight":0.9460664,"enabled":true,"innovation":182},{"in_node":61,"out_node":62,"weight":-0.64413,"enabled":true,"innovation":183},{"in_node":61,"out_node":63,"weight":-0.23207355,"enabled":true,"innovation":184},{"in_node":61,"out_node":64,"weight":0.3550763,"enabled":true,"innovation":185},{"in_node":36,"out_node":66,"weight":1.0,"enabled":true,"innovation":186},{"in_node":66,"out_node":64,"weight":0.9805918,"enabled":true,"innovation":187},{"in_node":58,"out_node":66,"weight":0.8702917,"enabled":true,"innovation":188},{"in_node":75,"out_node":66,"weight":-0.96173906,"enabled":true,"innovation":189},{"in_node":30,"out_node":77,"weight":1.0,"enabled":true,"innovation":190},{"in_node":77,"out_node":62,"weight":0.9884701,"enabled":true,"innovation":191},{"in_node":74,"out_node":67,"weight":0.8005805,"enabled":true,"innovation":192},{"in_node":14,"out_node":79,"weight":1.0,"enabled":true,"innovation":193},{"in_node":79,"out_node":64,"weight":0.40370154,"enabled":true,"innovation":194},{"in_node":55,"out_node":78,"weight":0.31541967,"enabled":true,"innovation":195},{"in_node":42,"out_node":66,"weight":-0.3514588,"enabled":true,"innovation":196},{"in_node":36,"out_node":86,"weight":1.0,"enabled":true,"innovation":197},{"in_node":87,"out_node":63,"weight":0.5343981,"enabled":true,"innovation":198},{"in_node":75,"out_node":79,"weight":-0.80712223,"enabled":true,"innovation":199},{"in_node":31,"out_node":66,"weight":-0.54117894,"enabled":true,"innovation":200},{"in_node":9,"out_node":88,"weight":1.0,"enabled":true,"innovation":201}],"fitness":115.25,"fitness_naive":0.0}